Metadata-Version: 1.0
Name: EquisCero
Version: 0.2
Summary: Tic Tac Toe Game for 2 players
Home-page: UNKNOWN
Author: Adriana Chavez
Author-email: adri92xd@gmail.com
License: UNKNOWN
Platform: UNKNOWN
